{
  "border_size": 1,
  "map_tiles": {
    "border": 5,
    "land": 2,
    "water": 1
  },
  "northern_port_list": [
    [
      0,
      4
    ],
    [
      2,
      6
    ],
    [
      4,
      6
    ],
    [
      6,
      6
    ],
    [
      8,
      6
    ],
    [
      10,
      6
    ],
    [
      10,
      8
    ],
    [
      14,
      10
    ]
  ],
  "southern_port_list": [
    [
      38,
      38
    ],
    [
      38,
      40
    ],
    [
      38,
      42
    ],
    [
      38,
      44
    ],
    [
      38,
      46
    ],
    [
      38,
      48
    ],
    [
      40,
      36
    ],
    [
      42,
      34
    ],
    [
      44,
      32
    ],
    [
      44,
      30
    ]
  ]
}